requests_panel/__init__.py
requests_panel/panel.py
requests_panel/tracker.py
requests_panel/templates/requests_panel/panel.html
django_requests_debug_toolbar-0.0.8.dist-info/LICENSE
django_requests_debug_toolbar-0.0.8.dist-info/METADATA
django_requests_debug_toolbar-0.0.8.dist-info/WHEEL
django_requests_debug_toolbar-0.0.8.dist-info/top_level.txt
django_requests_debug_toolbar-0.0.8.dist-info/RECORD
