Metadata-Version: 2.1
Name: django-requests-debug-toolbar
Version: 0.0.8
Summary: A Django Debug Toolbar panel for Requests
Home-page: https://github.com/marceltschoppch/django-requests-debug-toolbar
Author: Marcel Tschopp
Author-email: info@marceltschopp.ch
License: MIT
Keywords: django django-debug-toolbar requests debug toolbar
Classifier: Environment :: Web Environment
Classifier: Framework :: Django
Classifier: Framework :: Django :: 4.2
Classifier: Intended Audience :: Developers
Classifier: Operating System :: OS Independent
Classifier: License :: OSI Approved :: MIT License
Classifier: Programming Language :: Python
Classifier: Programming Language :: Python :: 3.11
Classifier: Programming Language :: Python :: 3.12
Classifier: Programming Language :: Python :: 3.13
Classifier: Programming Language :: Python :: 3.14
License-File: LICENSE
Requires-Dist: django-debug-toolbar >=2.2
